pyocd_bitbang/__init__.py
pyocd_bitbang/_version.py
pyocd_bitbang/bitbang_probe.py
pyocd_bitbang-1.0.2.dist-info/LICENSE
pyocd_bitbang-1.0.2.dist-info/METADATA
pyocd_bitbang-1.0.2.dist-info/WHEEL
pyocd_bitbang-1.0.2.dist-info/entry_points.txt
pyocd_bitbang-1.0.2.dist-info/top_level.txt
pyocd_bitbang-1.0.2.dist-info/zip-safe
pyocd_bitbang-1.0.2.dist-info/RECORD
