Metadata-Version: 2.1
Name: pyocd-bitbang
Version: 1.0.2
Summary: PyOCD debug probe plugin for Bitbang debug probes
Home-page: https://github.com/idex-biometrics/pyocd-bitbang
Download-URL: https://pypi.org/project/pyocd-bitbang/
Maintainer: Shareef Jalloq
Maintainer-email: shareef.jalloq@idexbiometrics.com
License: BSD-3-Clause
Project-URL: Documentation, https://pyocd.io/docs
Project-URL: Issues, https://github.com/idex-biometrics/pyocd-bitbang/issues
Keywords: SWD Bitbang PyOCD Plugin
Platform: Windows
Platform: Linux
Platform: macOS
Platform: BSD
Classifier: Programming Language :: Python :: 3.6
Classifier: Programming Language :: Python :: 3.7
Classifier: Programming Language :: Python :: 3.8
Classifier: Programming Language :: Python :: 3.9
Classifier: Programming Language :: Python :: 3.10
Classifier: Operating System :: MacOS :: MacOS X
Classifier: Operating System :: Microsoft :: Windows
Classifier: Operating System :: POSIX :: Linux
Classifier: Operating System :: POSIX :: BSD
Classifier: License :: OSI Approved :: BSD License
Classifier: Topic :: Scientific/Engineering
Classifier: Topic :: Software Development
Classifier: Topic :: Software Development :: Debuggers
Classifier: Topic :: Software Development :: Embedded Systems
Classifier: Topic :: System :: Hardware
Classifier: Topic :: Utilities
Requires-Python: >=3.6.0
License-File: LICENSE
